pydwrf/__init__.py
pydwrf/tes/__init__.py
pydwrf/tes/nc.py
pydwrf/tes/processing.py
pydwrf/tes/tes_core.py
pydwrf/tes/tes_time.py
pydwrf/tes/data/headers.txt
pydwrf/wrf/__init__.py
pydwrf/wrf/analysis.py
pydwrf/wrf/ascii.py
pydwrf/wrf/calculate_t15.py
pydwrf/wrf/dates.py
pydwrf/wrf/h5.py
pydwrf/wrf/icemass.py
pydwrf/wrf/info.py
pydwrf/wrf/nc.py
pydwrf/wrf/observe.py
pydwrf/wrf/observem24.py
pydwrf/wrf/plots.py
pydwrf/wrf/postprocess.py
pydwrf/wrf/postprocess_plots.py
pydwrf/wrf/scaled_ticks.py
pydwrf/wrf/special_variables.py
pydwrf/wrf/t15.py
pydwrf/wrf/twomoment.py
pydwrf/wrf/variables.py
pydwrf/wrf/wrf_exception.py
pydwrf/wrf/vl/__init__.py
pydwrf-0.15.dist-info/DESCRIPTION.rst
pydwrf-0.15.dist-info/METADATA
pydwrf-0.15.dist-info/RECORD
pydwrf-0.15.dist-info/WHEEL
pydwrf-0.15.dist-info/entry_points.txt
pydwrf-0.15.dist-info/metadata.json
pydwrf-0.15.dist-info/top_level.txt
