Metadata-Version: 2.0
Name: pydwrf
Version: 0.15
Summary: DART/WRF utilities in python
Home-page: UNKNOWN
Author: Christopher Lee
Author-email: lee@aeolisresearch.com
License: BSD
Platform: UNKNOWN
Requires-Dist: astropy
Requires-Dist: dwell
Requires-Dist: marstime
Requires-Dist: matplotlib
Requires-Dist: netCDF4
Requires-Dist: palettable
Requires-Dist: pandas
Requires-Dist: progressbar
Requires-Dist: seaborn
Requires-Dist: six
